planet_auth/__init__.py
planet_auth/auth.py
planet_auth/auth_client.py
planet_auth/auth_exception.py
planet_auth/constants.py
planet_auth/credential.py
planet_auth/py.typed
planet_auth/request_authenticator.py
planet_auth/storage_utils.py
planet_auth/util.py
planet_auth/internal/__init__.py
planet_auth/logging/__init__.py
planet_auth/logging/auth_logger.py
planet_auth/logging/events.py
planet_auth/none/__init__.py
planet_auth/none/noop_auth.py
planet_auth/oidc/__init__.py
planet_auth/oidc/auth_client.py
planet_auth/oidc/auth_client_default_authenticators.py
planet_auth/oidc/auth_client_with_client_pubkey.py
planet_auth/oidc/auth_client_with_client_secret.py
planet_auth/oidc/multi_validator.py
planet_auth/oidc/oidc_credential.py
planet_auth/oidc/request_authenticator.py
planet_auth/oidc/token_validator.py
planet_auth/oidc/util.py
planet_auth/oidc/api_clients/__init__.py
planet_auth/oidc/api_clients/api_client.py
planet_auth/oidc/api_clients/authorization_api_client.py
planet_auth/oidc/api_clients/device_authorization_api_client.py
planet_auth/oidc/api_clients/discovery_api_client.py
planet_auth/oidc/api_clients/introspect_api_client.py
planet_auth/oidc/api_clients/jwks_api_client.py
planet_auth/oidc/api_clients/oidc_request_auth.py
planet_auth/oidc/api_clients/revocation_api_client.py
planet_auth/oidc/api_clients/token_api_client.py
planet_auth/oidc/api_clients/userinfo_api_client.py
planet_auth/oidc/auth_clients/__init__.py
planet_auth/oidc/auth_clients/auth_code_flow.py
planet_auth/oidc/auth_clients/client_credentials_flow.py
planet_auth/oidc/auth_clients/client_validator.py
planet_auth/oidc/auth_clients/device_code_flow.py
planet_auth/oidc/auth_clients/resource_owner_flow.py
planet_auth/oidc/resources/__init__.py
planet_auth/oidc/resources/callback_acknowledgement.html
planet_auth/planet_legacy/__init__.py
planet_auth/planet_legacy/auth_client.py
planet_auth/planet_legacy/legacy_api_key.py
planet_auth/planet_legacy/request_authenticator.py
planet_auth-2.3.0.dist-info/licenses/LICENSE
planet_auth-2.3.0.dist-info/METADATA
planet_auth-2.3.0.dist-info/WHEEL
planet_auth-2.3.0.dist-info/entry_points.txt
planet_auth-2.3.0.dist-info/top_level.txt
planet_auth-2.3.0.dist-info/RECORD
